[
  {
    "id": "tap1",
    "title": "title1",
    "category": "tapestry",
    "description": "desc1",
    "image": "/works/tapestry_001.jpg",
    "aspect": "horizontal"
  },
  {
    "id": "tap2",
    "title": "title2",
    "category": "tapestry",
    "description": "desc2",
    "image": "/works/tapestry_002.jpg",
    "aspect": "square"
  },
  {
    "id": "tap3",
    "title": "title3",
    "category": "tapestry",
    "description": "desc3",
    "image": "/works/tapestry_003.jpg",
    "aspect": "square"
  },
  {
    "id": "tap4",
    "title": "title4",
    "category": "tapestry",
    "description": "desc4",
    "image": "/works/tapestry_004.jpg",
    "aspect": "horizontal"
  },
  {
    "id": "tap5",
    "title": "title5",
    "category": "tapestry",
    "description": "desc5",
    "image": "/works/tapestry_005.jpg",
    "aspect": "horizontal"
  },
  {
    "id": "tap6",
    "title": "title6",
    "category": "tapestry",
    "description": "desc6",
    "image": "/works/tapestry_006.jpg",
    "aspect": "horizontal"
  },
  {
    "id": "tap7",
    "title": "title7",
    "category": "tapestry",
    "description": "desc7",
    "image": "/works/tapestry_007.jpg",
    "aspect": "vertical"
  },
  {
    "id": "tap8",
    "title": "title8",
    "category": "tapestry",
    "description": "desc8",
    "image": "/works/tapestry_008.jpg",
    "aspect": "vertical"
  },
  {
    "id": "tap9",
    "title": "title9",
    "category": "tapestry",
    "description": "desc9",
    "image": "/works/tapestry_009.jpg",
    "aspect": "horizontal"
  },
  {
    "id": "tap10",
    "title": "title10",
    "category": "tapestry",
    "description": "desc10",
    "image": "/works/tapestry_010.jpg",
    "aspect": "horizontal"
  },
  {
    "id": "paint1",
    "title": "title_paint_1",
    "category": "painting",
    "description": "desc1",
    "image": "/works/painting_001.jpg",
    "aspect": "vertical"
  },
  {
    "id": "paint2",
    "title": "title_paint_2",
    "category": "painting",
    "description": "desc2",
    "image": "/works/painting_002.jpg",
    "aspect": "vertical"
  },
  {
    "id": "paint3",
    "title": "title_paint_3",
    "category": "painting",
    "description": "desc3",
    "image": "/works/painting_003.jpg",
    "aspect": "vertical"
  },
  {
    "id": "paint4",
    "title": "title_paint_4",
    "category": "painting",
    "description": "desc4",
    "image": "/works/painting_004.jpg",
    "aspect": "vertical"
  }
]